.gitignore
AUTHORS
MANIFEST.in
README.rst
setup.py
django_fab.egg-info/PKG-INFO
django_fab.egg-info/SOURCES.txt
django_fab.egg-info/dependency_links.txt
django_fab.egg-info/not-zip-safe
django_fab.egg-info/requires.txt
django_fab.egg-info/top_level.txt
djangofab/__init__.py
djangofab/api.py
djangofab/decorator.py
djangofab/django.py
djangofab/fab.cfg
djangofab/util.py
djangofab/vcs/__init__.py
djangofab/vcs/git.py
djangofab/vcs/svn.py
examples/fab.cfg
examples/fabfile-git.py
examples/fabfile-git.pyc
examples/fabfile-svn.py