Metadata-Version: 1.0
Name: django-fab
Version: 1.0.4
Summary: Common methods to help create fabric deplopment scripts for django
Home-page: http://github.com/hbussell/django-fab
Author: Harley Bussell
Author-email: modmac@gmail.com
License: GPL
Keywords: django fabric deployment
Platform: UNKNOWN
Classifier: License :: OSI Approved :: GNU General Public License (GPL)
Classifier: Programming Language :: Python
Classifier: Development Status :: 4 - Beta
Classifier: Intended Audience :: Developers
Classifier: Framework :: Django
Classifier: Environment :: Console
Classifier: Topic :: Software Development
Classifier: Topic :: System :: Software Distribution
